bismuthcore/__init__.py
bismuthcore/bismuthconfig.py
bismuthcore/bismuthcore.py
bismuthcore/block.py
bismuthcore/blocks.py
bismuthcore/clientcommands.py
bismuthcore/combackend.py
bismuthcore/compat.py
bismuthcore/decorators.py
bismuthcore/helpers.py
bismuthcore/rpcconnection.py
bismuthcore/simplecrypt.py
bismuthcore/tornadobackend.py
bismuthcore/transaction.py
bismuthcore/transactionslist.py
bismuthcore-0.0.19.dist-info/AUTHORS.rst
bismuthcore-0.0.19.dist-info/LICENSE
bismuthcore-0.0.19.dist-info/METADATA
bismuthcore-0.0.19.dist-info/WHEEL
bismuthcore-0.0.19.dist-info/top_level.txt
bismuthcore-0.0.19.dist-info/RECORD
