Metadata-Version: 2.1
Name: bismuthcore
Version: 0.0.19
Summary: Core Bismuth libraries for stable nodes versions.
Home-page: https://github.com/bismuthfoundation/bismuthcore
Author: EggdraSyl Bismuth Foundation
Author-email: dev@eggpool.net
License: MIT license
Keywords: bismuthcore
Platform: UNKNOWN
Classifier: Development Status :: 2 - Pre-Alpha
Classifier: Intended Audience :: Developers
Classifier: License :: OSI Approved :: MIT License
Classifier: Natural Language :: English
Classifier: Programming Language :: Python :: 3.5
Classifier: Programming Language :: Python :: 3.6
Classifier: Programming Language :: Python :: 3.7
Requires-Dist: polysign (>=0.1.0)
Requires-Dist: Tornado
Requires-Dist: ConcurrentLogHandler
Requires-Dist: requests
Requires-Dist: aioprocessing
